[
  {"code": "1000", "name": "Assets", "account_type": "ASSET", "parent_code": null},
  {"code": "1100", "name": "Current Assets", "account_type": "ASSET", "parent_code": "1000"},
  {"code": "1110", "name": "Cash and Cash Equivalents", "account_type": "ASSET", "parent_code": "1100"},
  {"code": "1111", "name": "Cash in Hand", "account_type": "ASSET", "parent_code": "1110"},
  {"code": "1112", "name": "Cash at Bank", "account_type": "ASSET", "parent_code": "1110"},
  {"code": "1120", "name": "Trade Receivables", "account_type": "ASSET", "parent_code": "1100"},
  {"code": "1121", "name": "Domestic Debtors", "account_type": "ASSET", "parent_code": "1120"},
  {"code": "1122", "name": "Foreign Debtors", "account_type": "ASSET", "parent_code": "1120"},
  {"code": "1130", "name": "Inventory", "account_type": "ASSET", "parent_code": "1100"},
  {"code": "1131", "name": "Trading Goods Inventory", "account_type": "ASSET", "parent_code": "1130"},
  {"code": "1132", "name": "Goods in Transit", "account_type": "ASSET", "parent_code": "1130"},
  {"code": "1140", "name": "Prepaid Expenses", "account_type": "ASSET", "parent_code": "1100"},
  {"code": "1200", "name": "Non-Current Assets", "account_type": "ASSET", "parent_code": "1000"},
  {"code": "1210", "name": "Property, Plant and Equipment", "account_type": "ASSET", "parent_code": "1200"},
  {"code": "1211", "name": "Warehouse and Storage", "account_type": "ASSET", "parent_code": "1210"},
  {"code": "1212", "name": "Delivery Vehicles", "account_type": "ASSET", "parent_code": "1210"},
  {"code": "1213", "name": "Office Equipment", "account_type": "ASSET", "parent_code": "1210"},
  {"code": "1220", "name": "Accumulated Depreciation", "account_type": "ASSET", "parent_code": "1200"},

  {"code": "2000", "name": "Liabilities", "account_type": "LIABILITY", "parent_code": null},
  {"code": "2100", "name": "Current Liabilities", "account_type": "LIABILITY", "parent_code": "2000"},
  {"code": "2110", "name": "Trade Payables", "account_type": "LIABILITY", "parent_code": "2100"},
  {"code": "2111", "name": "Domestic Creditors", "account_type": "LIABILITY", "parent_code": "2110"},
  {"code": "2112", "name": "Foreign Creditors", "account_type": "LIABILITY", "parent_code": "2110"},
  {"code": "2120", "name": "Short-term Borrowings", "account_type": "LIABILITY", "parent_code": "2100"},
  {"code": "2130", "name": "Accrued Expenses", "account_type": "LIABILITY", "parent_code": "2100"},
  {"code": "2131", "name": "Salaries Payable", "account_type": "LIABILITY", "parent_code": "2130"},
  {"code": "2132", "name": "Tax Payable", "account_type": "LIABILITY", "parent_code": "2130"},
  {"code": "2133", "name": "VAT Payable", "account_type": "LIABILITY", "parent_code": "2130"},
  {"code": "2200", "name": "Non-Current Liabilities", "account_type": "LIABILITY", "parent_code": "2000"},

  {"code": "3000", "name": "Equity", "account_type": "EQUITY", "parent_code": null},
  {"code": "3100", "name": "Share Capital", "account_type": "EQUITY", "parent_code": "3000"},
  {"code": "3200", "name": "Retained Earnings", "account_type": "EQUITY", "parent_code": "3000"},

  {"code": "4000", "name": "Revenue", "account_type": "REVENUE", "parent_code": null},
  {"code": "4100", "name": "Sales Revenue", "account_type": "REVENUE", "parent_code": "4000"},
  {"code": "4110", "name": "Domestic Sales", "account_type": "REVENUE", "parent_code": "4100"},
  {"code": "4120", "name": "Export Sales", "account_type": "REVENUE", "parent_code": "4100"},
  {"code": "4200", "name": "Other Income", "account_type": "REVENUE", "parent_code": "4000"},

  {"code": "5000", "name": "Cost of Goods Sold", "account_type": "EXPENSE", "parent_code": null},
  {"code": "5100", "name": "Cost of Purchases", "account_type": "EXPENSE", "parent_code": "5000"},
  {"code": "5200", "name": "Freight Inward", "account_type": "EXPENSE", "parent_code": "5000"},
  {"code": "5300", "name": "Import Duties and Taxes", "account_type": "EXPENSE", "parent_code": "5000"},

  {"code": "6000", "name": "Operating Expenses", "account_type": "EXPENSE", "parent_code": null},
  {"code": "6100", "name": "Distribution Costs", "account_type": "EXPENSE", "parent_code": "6000"},
  {"code": "6110", "name": "Freight Outward", "account_type": "EXPENSE", "parent_code": "6100"},
  {"code": "6120", "name": "Warehousing Costs", "account_type": "EXPENSE", "parent_code": "6100"},
  {"code": "6200", "name": "Selling Expenses", "account_type": "EXPENSE", "parent_code": "6000"},
  {"code": "6210", "name": "Sales Salaries", "account_type": "EXPENSE", "parent_code": "6200"},
  {"code": "6220", "name": "Marketing", "account_type": "EXPENSE", "parent_code": "6200"},
  {"code": "6300", "name": "Administrative Expenses", "account_type": "EXPENSE", "parent_code": "6000"},
  {"code": "6310", "name": "Office Salaries", "account_type": "EXPENSE", "parent_code": "6300"},
  {"code": "6320", "name": "Rent", "account_type": "EXPENSE", "parent_code": "6300"},
  {"code": "6330", "name": "Utilities", "account_type": "EXPENSE", "parent_code": "6300"},
  {"code": "6340", "name": "Depreciation", "account_type": "EXPENSE", "parent_code": "6300"},

  {"code": "7000", "name": "Financial Expenses", "account_type": "EXPENSE", "parent_code": null},
  {"code": "7100", "name": "Interest Expense", "account_type": "EXPENSE", "parent_code": "7000"},
  {"code": "7200", "name": "Bank Charges", "account_type": "EXPENSE", "parent_code": "7000"}
]
